odoo/addons/base_force_record_noupdate/README.rst
odoo/addons/base_force_record_noupdate/__init__.py
odoo/addons/base_force_record_noupdate/__manifest__.py
odoo/addons/base_force_record_noupdate/i18n/base_force_record_noupdate.pot
odoo/addons/base_force_record_noupdate/i18n/it.po
odoo/addons/base_force_record_noupdate/models/__init__.py
odoo/addons/base_force_record_noupdate/models/ir_model.py
odoo/addons/base_force_record_noupdate/models/ir_model_data.py
odoo/addons/base_force_record_noupdate/readme/CONTRIBUTORS.rst
odoo/addons/base_force_record_noupdate/readme/DESCRIPTION.rst
odoo/addons/base_force_record_noupdate/readme/USAGE.rst
odoo/addons/base_force_record_noupdate/static/description/icon.png
odoo/addons/base_force_record_noupdate/static/description/index.html
odoo/addons/base_force_record_noupdate/tests/__init__.py
odoo/addons/base_force_record_noupdate/tests/test_base_force_record_noupdate.py
odoo/addons/base_force_record_noupdate/views/ir_model.xml
odoo14_addon_base_force_record_noupdate-14.0.1.0.1.dev3.dist-info/METADATA
odoo14_addon_base_force_record_noupdate-14.0.1.0.1.dev3.dist-info/WHEEL
odoo14_addon_base_force_record_noupdate-14.0.1.0.1.dev3.dist-info/top_level.txt
odoo14_addon_base_force_record_noupdate-14.0.1.0.1.dev3.dist-info/RECORD
